topsis_aarushpruthi_102203793/__init__.py
topsis_aarushpruthi_102203793/topsis.py
Topsis_AarushPruthi_102203793-1.0.2.dist-info/LICENSE.unknown
Topsis_AarushPruthi_102203793-1.0.2.dist-info/METADATA
Topsis_AarushPruthi_102203793-1.0.2.dist-info/WHEEL
Topsis_AarushPruthi_102203793-1.0.2.dist-info/top_level.txt
Topsis_AarushPruthi_102203793-1.0.2.dist-info/RECORD
